ldpc/__init__.py
ldpc/base_code.py
ldpc/wifi_spec_codes.py
ldpc/code_specs/4098_3095_non_sys_h.alist
ldpc/code_specs/Mackay_96.3.963.alist
ldpc/code_specs/ieee802.3_G.alist
ldpc/code_specs/systematic_4098_3095.alist
ldpc/code_specs/ieee802.11/N1296_R12.qc
ldpc/code_specs/ieee802.11/N1296_R23.qc
ldpc/code_specs/ieee802.11/N1296_R34.qc
ldpc/code_specs/ieee802.11/N1296_R56.qc
ldpc/code_specs/ieee802.11/N1944_R12.qc
ldpc/code_specs/ieee802.11/N1944_R23.qc
ldpc/code_specs/ieee802.11/N1944_R34.qc
ldpc/code_specs/ieee802.11/N1944_R56.qc
ldpc/code_specs/ieee802.11/N648_R12.qc
ldpc/code_specs/ieee802.11/N648_R23.qc
ldpc/code_specs/ieee802.11/N648_R34.qc
ldpc/code_specs/ieee802.11/N648_R56.qc
ldpc/decoder/__init__.py
ldpc/decoder/common.py
ldpc/decoder/gal_bf.py
ldpc/decoder/graph.py
ldpc/decoder/ieee802_11_decoder.py
ldpc/decoder/log_spa_decoder.py
ldpc/decoder/node.py
ldpc/decoder/pbf_decoder.py
ldpc/decoder/wbf.py
ldpc/encoder/__init__.py
ldpc/encoder/base_encoder.py
ldpc/encoder/generator_based_encoder.py
ldpc/encoder/h_based_encoder.py
ldpc/encoder/ieee802_11_encoder.py
ldpc/utils/__init__.py
ldpc/utils/a_list_format.py
ldpc/utils/custom_exceptions.py
ldpc/utils/frame.py
ldpc/utils/qc_format.py
sim_ldpc-0.3.5.dist-info/LICENSE
sim_ldpc-0.3.5.dist-info/METADATA
sim_ldpc-0.3.5.dist-info/WHEEL
sim_ldpc-0.3.5.dist-info/top_level.txt
sim_ldpc-0.3.5.dist-info/RECORD
