Metadata-Version: 2.1
Name: sim-ldpc
Version: 0.3.5
Summary: Simulate LDPC codes, both encoding and decoding
Home-page: https://github.com/YairMZ/LDPC
Author: Yair Mazal
Author-email: yairmazal@gmail.com
License: MIT
Keywords: LDPC,Belief Propagation,SPA,Tanner Graph,IEEE 802.11
Classifier: License :: OSI Approved :: MIT License
Classifier: Programming Language :: Python :: 3
Classifier: Intended Audience :: Developers
Classifier: Intended Audience :: Education
Classifier: Intended Audience :: Science/Research
Classifier: Intended Audience :: Telecommunications Industry
Classifier: Topic :: Scientific/Engineering
License-File: LICENSE
Requires-Dist: numpy
Requires-Dist: networkx
Requires-Dist: scipy
Requires-Dist: bitstring
